coil_python/__init__.py
coil_python/__main__.py
coil_python/compare.py
coil_python/dec.py
coil_python/enc.py
coil_python/stats.py
coil_python/visual.py
coil_python-0.1.10.dist-info/METADATA
coil_python-0.1.10.dist-info/WHEEL
coil_python-0.1.10.dist-info/entry_points.txt
coil_python-0.1.10.dist-info/top_level.txt
coil_python-0.1.10.dist-info/RECORD
